video_audio_merge_mcp/__init__.py
video_audio_merge_mcp/main.py
mcpcn_video_audio_merge_mcp-0.1.0.dist-info/METADATA
mcpcn_video_audio_merge_mcp-0.1.0.dist-info/WHEEL
mcpcn_video_audio_merge_mcp-0.1.0.dist-info/entry_points.txt
mcpcn_video_audio_merge_mcp-0.1.0.dist-info/RECORD
