Metadata-Version: 2.4
Name: mcpcn-video-audio-merge-mcp
Version: 0.1.0
Summary: MCP server for merging video and audio files
Author-email: Your Name <your.email@example.com>
License: MIT
Keywords: audio,ffmpeg,mcp,merge,video
Classifier: Development Status :: 4 - Beta
Classifier: Intended Audience :: Developers
Classifier: License :: OSI Approved :: MIT License
Classifier: Programming Language :: Python :: 3
Classifier: Programming Language :: Python :: 3.12
Classifier: Topic :: Multimedia :: Sound/Audio
Classifier: Topic :: Multimedia :: Video
Requires-Python: >=3.12
Requires-Dist: ffmpeg-python>=0.2.0
Requires-Dist: mcp[cli]>=1.9.0
